LICENSE
README.md
setup.py
dockerclient/__init__.py
dockerclient.egg-info/PKG-INFO
dockerclient.egg-info/SOURCES.txt
dockerclient.egg-info/dependency_links.txt
dockerclient.egg-info/top_level.txt